README
setup.py
done/Commands.py
done/Config.py
done/Queries.py
done/Tasks.py
done/__init__.py
done/done.py
done/termcolor.py
done.egg-info/PKG-INFO
done.egg-info/SOURCES.txt
done.egg-info/dependency_links.txt
done.egg-info/entry_points.txt
done.egg-info/top_level.txt
parsedatetime/__init__.py
parsedatetime/parsedatetime.py
parsedatetime/parsedatetime_consts.py
parsedatetime/t2.py
sql_interp/__init__.py
sql_interp/esc_types.py
sql_interp/sql_interp.py