Metadata-Version: 1.0
Name: done
Version: 1.0.4
Summary: simple, elegant command line todo list tool
Home-page: http://github.com/nathanielksmith/done
Author: Nathaniel K Smith
Author-email: nathanielksmith@gmail.com
License: UNKNOWN
Platform: UNKNOWN
Classifier: Development Status :: 4 - Beta
Classifier: Environment :: Console
Classifier: Intended Audience :: Developers
Classifier: License :: OSI Approved :: GNU General Public License (GPL)
Classifier: Operating System :: OS Independent
Classifier: Programming Language :: Python
Classifier: Topic :: Utilities
